drawgly/__init__.py
drawgly/draw.py
drawgly-0.1.0.dist-info/LICENSE
drawgly-0.1.0.dist-info/METADATA
drawgly-0.1.0.dist-info/WHEEL
drawgly-0.1.0.dist-info/RECORD
