Metadata-Version: 2.1
Name: drawgly
Version: 0.1.0
Summary: 
Home-page: https://github.com/fubin1999/drawgly
License: MIT
Author: fubin1999
Author-email: 65430559+fubin1999@users.noreply.github.com
Requires-Python: >=3.10,<4.0
Classifier: License :: OSI Approved :: MIT License
Classifier: Programming Language :: Python :: 3
Classifier: Programming Language :: Python :: 3.10
Classifier: Programming Language :: Python :: 3.11
Requires-Dist: requests (>=2.28.2,<3.0.0)
Project-URL: Repository, https://github.com/fubin1999/drawgly
